sonnerrise_promo/__init__.py
sonnerrise_promo/cli.py
sonnerrise_promo/models.py
sonnerrise_promo/repository.py
sonnerrise_promo/schemas.py
sonnerrise_promo-0.1.0.dist-info/METADATA
sonnerrise_promo-0.1.0.dist-info/WHEEL
sonnerrise_promo-0.1.0.dist-info/entry_points.txt
sonnerrise_promo-0.1.0.dist-info/RECORD
