Metadata-Version: 2.4
Name: sonnerrise-promo
Version: 0.1.0
Summary: Promotion module for Sonnerrise - track promotion management
Author-email: Konstantin Boyandin <developer@boyandin.com>
License-Expression: MIT
Requires-Python: >=3.11
Requires-Dist: pydantic>=2.0
Requires-Dist: sonnerrise-core>=0.1.0
Requires-Dist: sonnerrise-tracks>=0.1.0
Provides-Extra: dev
Requires-Dist: pytest-cov>=4.0; extra == 'dev'
Requires-Dist: pytest>=7.0; extra == 'dev'
